{
  "url": "https://www2.hkej.com/instantnews/current/article/4290985/%E5%AE%8F%E7%A6%8F%E8%8B%91%E5%A4%A7%E7%81%AB%E4%B8%A8%E6%B3%95%E5%BA%AD%E6%89%B9%E5%87%86%E8%A7%A3%E6%95%A3%E6%B3%95%E5%9C%98%E7%AE%A1%E5%A7%94%E6%9C%83+%E7%94%B1%E8%8F%AF%E6%87%8B%E5%AD%90%E4%BC%81%E5%90%88%E5%AE%89%E6%8E%A5%E7%AE%A1",
  "title": "宏福苑大火丨法庭批准解散法團管委會 由華懋子企合安接管",
  "source": "hkej",
  "source_file": "content/news/hkej/README.md",
  "scraped_at": "2026-01-06T22:41:17.730452",
  "archive_path": "content/news/hkej/archive/宏福苑大火丨法庭批准解散法團管委會-由華懋子企合安接管"
}